influxdb_client_3/__init__.py
pyinflux3-0.9.2.dist-info/METADATA
pyinflux3-0.9.2.dist-info/WHEEL
pyinflux3-0.9.2.dist-info/top_level.txt
pyinflux3-0.9.2.dist-info/RECORD
