Metadata-Version: 2.1
Name: pyinflux3
Version: 0.9.2
Summary: Community Python client for InfluxDB IOx
Home-page: https://github.com/InfluxCommunity/pyinflux3
Author: InfluxData
Author-email: contact@influxdata.com
Classifier: Development Status :: 4 - Beta
Classifier: Intended Audience :: Developers
Classifier: License :: OSI Approved :: MIT License
Classifier: Programming Language :: Python :: 3
Classifier: Programming Language :: Python :: 3.6
Classifier: Programming Language :: Python :: 3.7
Classifier: Programming Language :: Python :: 3.8
Classifier: Programming Language :: Python :: 3.9
Classifier: Programming Language :: Python :: 3.10
Requires-Dist: pyarrow
Requires-Dist: flightsql-dbapi
Requires-Dist: influxdb-client
Provides-Extra: cli
Requires-Dist: pyinflux3-cli ; extra == 'cli'
